LICENSE.TXT
MANIFEST.in
README.md
pyproject.toml
setup.cfg
setup.py
bin/abconfig
bin/abdiagnose.py
bin/abrun.py
bin/abrun.sh
bin/apprun.sh
doc/src/Makefile
doc/src/apiref.rst
doc/src/build_docs.sh
doc/src/changes.rst
doc/src/citing.rst
doc/src/conf.py
doc/src/index.rst
doc/src/installing.rst
doc/src/intro.rst
doc/src/invoking.rst
doc/src/processors.rst
doc/src/sys_config.rst
doc/src/_static/afterburner_32x32.ico
doc/src/_themes/sphinx_rtd_theme/LICENSE
doc/src/_themes/sphinx_rtd_theme/__init__.py
doc/src/_themes/sphinx_rtd_theme/breadcrumbs.html
doc/src/_themes/sphinx_rtd_theme/footer.html
doc/src/_themes/sphinx_rtd_theme/layout.html
doc/src/_themes/sphinx_rtd_theme/layout_old.html
doc/src/_themes/sphinx_rtd_theme/search.html
doc/src/_themes/sphinx_rtd_theme/searchbox.html
doc/src/_themes/sphinx_rtd_theme/theme.conf
doc/src/_themes/sphinx_rtd_theme/versions.html
doc/src/_themes/sphinx_rtd_theme/static/css/badge_only.css
doc/src/_themes/sphinx_rtd_theme/static/css/badge_only.css.map
doc/src/_themes/sphinx_rtd_theme/static/css/theme.css
doc/src/_themes/sphinx_rtd_theme/static/css/theme.css.map
doc/src/_themes/sphinx_rtd_theme/static/fonts/FontAwesome.otf
doc/src/_themes/sphinx_rtd_theme/static/fonts/Inconsolata-Bold.ttf
doc/src/_themes/sphinx_rtd_theme/static/fonts/Inconsolata-Regular.ttf
doc/src/_themes/sphinx_rtd_theme/static/fonts/Lato-Bold.ttf
doc/src/_themes/sphinx_rtd_theme/static/fonts/Lato-Regular.ttf
doc/src/_themes/sphinx_rtd_theme/static/fonts/RobotoSlab-Bold.ttf
doc/src/_themes/sphinx_rtd_theme/static/fonts/RobotoSlab-Regular.ttf
doc/src/_themes/sphinx_rtd_theme/static/fonts/fontawesome-webfont.eot
doc/src/_themes/sphinx_rtd_theme/static/fonts/fontawesome-webfont.svg
doc/src/_themes/sphinx_rtd_theme/static/fonts/fontawesome-webfont.ttf
doc/src/_themes/sphinx_rtd_theme/static/fonts/fontawesome-webfont.woff
doc/src/_themes/sphinx_rtd_theme/static/js/modernizr.min.js
doc/src/_themes/sphinx_rtd_theme/static/js/theme.js
doc/src/dev_guide/apps.rst
lib/metoffice_afterburner.egg-info/PKG-INFO
lib/metoffice_afterburner.egg-info/SOURCES.txt
lib/metoffice_afterburner.egg-info/dependency_links.txt
lib/metoffice_afterburner.egg-info/not-zip-safe
lib/metoffice_afterburner.egg-info/requires.txt
lib/metoffice_afterburner.egg-info/top_level.txt
