Metadata-Version: 2.4
Name: metoffice-afterburner
Version: 1.3.4
Summary: Tools and apps for processing numerical climate model data
Home-page: https://code.metoffice.gov.uk/trac/afterburner
Author: UK Met Office
Author-email: afterburner@metoffice.gov.uk
Classifier: Programming Language :: Python :: 3
Classifier: License :: OSI Approved :: BSD License
Classifier: Operating System :: OS Independent
Requires-Python: >=2.7
License-File: LICENSE.TXT
Requires-Dist: scitools-iris>=2.1
Requires-Dist: pyparsing>=2
Requires-Dist: windspharm
Provides-Extra: test
Requires-Dist: pytest; extra == "test"
Dynamic: author
Dynamic: author-email
Dynamic: classifier
Dynamic: description
Dynamic: description-content-type
Dynamic: home-page
Dynamic: license-file
Dynamic: provides-extra
Dynamic: requires-dist
Dynamic: requires-python
Dynamic: summary
